khx_color_text/__init__.py
khx_color_text/cli.py
khx_color_text/core.py
khx_color_text/colors/__init__.py
khx_color_text/colors/custom.py
khx_color_text/colors/predefined.py
khx_color_text/colors/utils.py
khx_color_text/examples/__init__.py
khx_color_text/examples/advanced_examples.py
khx_color_text/examples/basic_examples.py
khx_color_text/examples/color_showcase.py
khx_color_text/lines/README.md
khx_color_text/lines/__init__.py
khx_color_text/lines/characters.py
khx_color_text/lines/core.py
khx_color_text/lines/examples.py
khx_color_text/styles/__init__.py
khx_color_text/styles/background.py
khx_color_text/styles/text_styles.py
khx_color_text-0.3.0.dist-info/METADATA
khx_color_text-0.3.0.dist-info/WHEEL
khx_color_text-0.3.0.dist-info/entry_points.txt
khx_color_text-0.3.0.dist-info/licenses/LICENSE
khx_color_text-0.3.0.dist-info/RECORD
