Metadata-Version: 2.4
Name: khx_color_text
Version: 0.3.0
Summary: A comprehensive Python package for printing colored and styled text in the terminal with decorative lines, extensive customization options, and IDE autocomplete support
Project-URL: Homepage, https://github.com/Khader-X/khx_color_text
Project-URL: Repository, https://github.com/Khader-X/khx_color_text
Project-URL: Issues, https://github.com/Khader-X/khx_color_text/issues
Author-email: ABUELTAYEF Khader <abueltayef.khader@gmail.com>
License: MIT
License-File: LICENSE
Classifier: Development Status :: 4 - Beta
Classifier: Intended Audience :: Developers
Classifier: License :: OSI Approved :: MIT License
Classifier: Programming Language :: Python :: 3
Classifier: Programming Language :: Python :: 3.9
Classifier: Programming Language :: Python :: 3.10
Classifier: Programming Language :: Python :: 3.11
Classifier: Programming Language :: Python :: 3.12
Classifier: Topic :: Software Development :: Libraries :: Python Modules
Classifier: Topic :: Terminals
Requires-Python: >=3.9
Requires-Dist: colorama>=0.4.6
Provides-Extra: docs
Requires-Dist: matplotlib>=3.7; extra == 'docs'
Requires-Dist: mkdocs-material>=9.6; extra == 'docs'
Requires-Dist: mkdocs>=1.6; extra == 'docs'
Requires-Dist: rich>=13; extra == 'docs'
Provides-Extra: test
Requires-Dist: pytest>=8; extra == 'test'
